CHANGELOG.txt
LICENSE.GPL
LICENSE.txt
MANIFEST.in
README.rst
bootstrap.py
buildout.cfg
setup.py
collective/__init__.py
collective.captcha.egg-info/PKG-INFO
collective.captcha.egg-info/SOURCES.txt
collective.captcha.egg-info/dependency_links.txt
collective.captcha.egg-info/entry_points.txt
collective.captcha.egg-info/namespace_packages.txt
collective.captcha.egg-info/not-zip-safe
collective.captcha.egg-info/requires.txt
collective.captcha.egg-info/top_level.txt
collective/captcha/__init__.py
collective/captcha/configure.zcml
collective/captcha/browser/__init__.py
collective/captcha/browser/arevmoit.bdf
collective/captcha/browser/captcha.py
collective/captcha/browser/captcha.txt
collective/captcha/browser/configure.zcml
collective/captcha/browser/interfaces.py
collective/captcha/browser/tests.py
collective/captcha/browser/waveIndex.zip
collective/captcha/form/__init__.py
collective/captcha/form/captcha.txt
collective/captcha/form/configure.zcml
collective/captcha/form/field.py
collective/captcha/form/interfaces.py
collective/captcha/form/widget.py
parts/instance/bin/README.txt
parts/instance/etc/site.zcml
parts/instance/etc/package-includes/001-collective.captcha-configure.zcml
parts/instance/var/README.txt