Metadata-Version: 1.0
Name: collective.captcha
Version: 1.7
Summary: Stateless captcha generation and verification
Home-page: https://github.com/mjpieters/collective.captcha
Author: Jarn
Author-email: info@jarn.com
License: GPL
Keywords: captcha stateless
Platform: UNKNOWN
Classifier: Development Status :: 5 - Production/Stable
Classifier: Framework :: Plone
Classifier: Framework :: Zope2
Classifier: Intended Audience :: Developers
Classifier: License :: OSI Approved :: GNU General Public License (GPL)
Classifier: Programming Language :: Python
Classifier: Topic :: Software Development :: Libraries :: Python Modules
